{"cameraMode":{"drawMode":0,"name":"Shaded","section":"Shading Mode"},"sceneLighting":true,"audioPlay":false,"sceneViewState":{"showFog":true,"showMaterialUpdate":false,"showSkybox":true,"showFlares":true,"showImageEffects":true,"showParticleSystems":true},"in2DMode":false,"pivot":{"x":-15.386874198913575,"y":14.092945098876954,"z":98.74089813232422},"rotation":{"x":0.16254830360412599,"y":0.05177604407072067,"z":-0.008541633374989033,"w":0.9853043556213379},"size":53.40924835205078,"orthographic":false}