{"cameraMode":{"drawMode":0,"name":"Shaded","section":"Shading Mode"},"sceneLighting":true,"audioPlay":false,"sceneViewState":{"showFog":true,"showMaterialUpdate":false,"showSkybox":true,"showFlares":true,"showImageEffects":true,"showParticleSystems":true},"in2DMode":false,"pivot":{"x":169.1442413330078,"y":353.7808837890625,"z":51.6549072265625},"rotation":{"x":0.10018471628427506,"y":-0.05370150879025459,"z":0.005415659863501787,"w":0.9935043454170227},"size":1909.8692626953125,"orthographic":false}